LICENSE
LICENSE.Rfam
LICENSE.SILVA
MANIFEST.in
README.md
setup.py
barrnap/barrnap.py
barrnap.egg-info/PKG-INFO
barrnap.egg-info/SOURCES.txt
barrnap.egg-info/dependency_links.txt
barrnap.egg-info/top_level.txt
barrnap/db/arc.hmm
barrnap/db/bac.hmm
barrnap/db/euk.hmm
barrnap/db/mito.hmm
barrnap/examples/archaea.fna
barrnap/examples/bacteria.fna
barrnap/examples/empty.fna
barrnap/examples/fungus.fna
barrnap/examples/mitochondria.fna
barrnap/examples/nohits.fna
barrnap/examples/null.fna
barrnap/examples/protein.fna
barrnap/examples/small.fna