Metadata-Version: 1.1
Name: barrnap
Version: 0.0.5
Summary: python package for barrnap 
Home-page: https://github.com/nickp60/barrnap
Author: Nick Waters
Author-email: nickp60@gmail.com
License: GNU General Public License v3.0
Keywords: bioinformatics
Platform: UNKNOWN
Classifier: Development Status :: 3 - Alpha
Classifier: Intended Audience :: Developers
Classifier: Topic :: Software Development :: Build Tools
Classifier: Programming Language :: Python :: 3.5
Classifier: Programming Language :: Python :: 3.6
